{
  "name": "Home",
  "path": "/",
  "sections": {
    "variants": [
      {
        "rule": {
          "includes": "otica-isabela.deco.site",
          "__resolveType": "$live/matchers/MatchHost.ts"
        },
        "value": [
          {
            "__resolveType": "SEODefault"
          },
          {
            "__resolveType": "Header - 01"
          },
          {
            "__resolveType": "website/sections/Rendering/Lazy.tsx",
            "section": {
              "__resolveType": "New Carrossel"
            }
          },
          {
            "__resolveType": "Produtos Visitados - Home & PDP"
          },
          {
            "__resolveType": "site/sections/Product/ProductBestDailyOffers.tsx",
            "customer": {
              "__resolveType": "site/loaders/store/auth.ts"
            },
            "products": {
              "__resolveType": "site/loaders/product/productList.ts",
              "id": [],
              "offset": 9,
              "ordenacao": "mais-vendidos",
              "ofertasDia": true,
              "filtrosDinamicos": [],
              "somenteCronometrosAtivos": false
            }
          },
          {
            "__resolveType": "Depoimentos"
          },
          {
            "__resolveType": "website/sections/Rendering/Deferred.tsx",
            "sections": [
              {
                "__resolveType": "Para as Mulheres"
              },
              {
                "__resolveType": "Clipon Novidades"
              },
              {
                "__resolveType": "Para os Homens"
              },
              {
                "__resolveType": "Banners Categorias"
              },
              {
                "__resolveType": "Clipon Feminino"
              },
              {
                "__resolveType": "Banners Sobre a Loja"
              }
            ]
          },
          {
            "__resolveType": "Sobre a Loja"
          },
          {
            "__resolveType": "FAQ - 02"
          },
          {
            "__resolveType": "Footer - 01"
          },
          {
            "__resolveType": "wpp-cta"
          }
        ]
      },
      {
        "rule": {
          "__resolveType": "website/matchers/always.ts"
        },
        "value": [
          {
            "__resolveType": "SEODefault"
          },
          {
            "__resolveType": "Header - 01"
          },
          {
            "__resolveType": "New Carrossel"
          },
          {
            "__resolveType": "Produtos Visitados - Home & PDP"
          },
          {
            "customer": {
              "__resolveType": "site/loaders/store/auth.ts"
            },
            "products": {
              "__resolveType": "offers"
            },
            "__resolveType": "site/sections/Product/ProductBestDailyOffers.tsx"
          },
          {
            "text": {
              "content": "<h2><span style=\"color: rgb(62, 62, 62);\" data-mce-style=\"color: rgb(62, 62, 62);\"><strong><span style=\"font-size: 24pt;\" data-mce-style=\"font-size: 24pt;\">Ganhamos o Prêmio Reclame Aqui 2024!﻿</span></strong></span></h2><p style=\"line-height: 1.3;\" data-mce-style=\"line-height: 1.3;\"><br data-mce-bogus=\"1\"></p><p style=\"line-height: 1.3;\" data-mce-style=\"line-height: 1.3;\"><span style=\"font-size: 14pt; color: rgb(62, 62, 62);\" data-mce-style=\"font-size: 14pt; color: rgb(62, 62, 62);\">Está comprovado que é possível entregar óculos com preço justo, qualidade e </span></p><p style=\"line-height: 1.3;\" data-mce-style=\"line-height: 1.3;\"><span style=\"font-size: 14pt; color: rgb(62, 62, 62);\" data-mce-style=\"font-size: 14pt; color: rgb(62, 62, 62);\">o melhor atendimento do Brasil.&nbsp;<span class=\"x19la9d6 x1fc57z9 x6ikm8r x10wlt62 x19co3pv x1g5zs5t xfibh0p xiy17q3 x1xsqp64 x1lkfr7t xexx8yu x4uap5 x18d9i69 xkhd6sd\"><span class=\"xrtxmta x1bhl96m\">🏆</span></span></span></p><p style=\"line-height: 1.3;\" data-mce-style=\"line-height: 1.3;\"><br data-mce-bogus=\"1\"></p>",
              "mobilePadding": {
                "top": 0,
                "left": 0,
                "right": 0,
                "bottom": 0
              },
              "verticalAlign": "center",
              "desktopPadding": {
                "top": 0,
                "left": 0,
                "right": 0,
                "bottom": 0
              }
            },
            "media": {
              "tag": null,
              "mobile": {
                "alt": "atendimento",
                "src": "https://assets.decocache.com/otica-isabela/4db4d029-f0e8-4ec6-a48e-2b209395a4fd/Banner-mobile-Trofeu.jpg",
                "height": 600,
                "width": 800
              },
              "desktop": {
                "alt": "atendimento",
                "src": "https://assets.decocache.com/otica-isabela/9e1dc7c4-bb1c-433f-b4cb-5166be88c93f/Banner-Desk-site-Equipe-04.jpg",
                "height": 500,
                "width": 1100
              },
              "position": "left",
              "thumbnail": {
                "src": "https://deco-sites-assets.s3.sa-east-1.amazonaws.com/otica-isabela/23fa261d-9d87-415d-b172-d2894d6155c0/Banner-Desk.jpg"
              }
            },
            "button": {
              "href": "https://api.whatsapp.com/send?phone=5516991815926&text=%C3%93la,%20preciso%20de%20atendimento",
              "color": "#06a9f5",
              "label": "Conte com a gente!",
              "style": "filled",
              "labelColor": "#ffffff",
              "horizontalAlign": "center",
              "blank": true
            },
            "seeMore": null,
            "container": false,
            "linksGrid": null,
            "__resolveType": "site/sections/Content/RichText.tsx",
            "backgroundColor": "#c9effd"
          },
          {
            "__resolveType": "Para as Mulheres"
          },
          {
            "__resolveType": "Clipon Feminino"
          },
          {
            "__resolveType": "Depoimentos"
          },
          {
            "__resolveType": "FAQ - 02"
          },
          {
            "__resolveType": "Sobre a Loja"
          },
          {
            "__resolveType": "Footer - 01"
          },
          {
            "__resolveType": "wpp-cta"
          }
        ]
      }
    ],
    "__resolveType": "$live/flags/multivariate.ts"
  },
  "__resolveType": "$live/pages/LivePage.tsx"
}