{"text":{"content":"<h3><strong><span style=\"font-size: 18pt;\" data-mce-style=\"font-size: 18pt;\">Aprenda a usar o Provador na prática﻿</span></strong></h3><p><strong><span style=\"font-size: 18pt;\" data-mce-style=\"font-size: 18pt;\"><br data-mce-bogus=\"1\"></span></strong></p><p><span style=\"font-size: 12pt;\" data-mce-style=\"font-size: 12pt;\">Veja esse vídeo e desfrute das diversas armações em nosso site!</span></p>","verticalAlign":"center"},"media":{"position":"left","videoUrl":"https://www.youtube.com/embed/yamlG-ZNM7w","thumbnail":{"alt":"Provador de óculos online","src":"https://ozksgdmyrqcxcwhnbepg.supabase.co/storage/v1/object/public/assets/1803/7811fb6c-ee79-4d0f-a4c0-0d1a3f0fdbfb","width":1000,"height":500,"preload":false}},"button":{"href":"https://www.youtube.com/embed/yamlG-ZNM7w","color":"#42c2ff","label":"Veja o vídeo","style":"filled","labelColor":"#ffffff","horizontalAlign":"center"},"seeMore":null,"linksGrid":null,"__resolveType":"site/sections/Content/RichText.tsx","backgroundColor":"#f7f7f7"}